{
    "Careers_Female_Male": {
        "A_key": "Женские атрибуты",
        "B_key": "Мужские атрибуты",
        "Careers": [
            "техник",
            "бухгалтер",
            "руководитель",
            "инженер",
            "рабочий",
            "воспитатель",
            "клерк",
            "консультант",
            "инспектор",
            "механик",
            "менеджер",
            "терапевт",
            "администратор",
            "продавец",
            "секретарь",
            "библиотекарь",
            "советник",
            "фармацевт",
            "уборщик",
            "психолог",
            "врач",
            "плотник",
            "медсестра",
            "следователь",
            "бармен",
            "специалист",
            "электрик",
            "офицер",
            "патолог",
            "учитель",
            "юрист",
            "планировщик",
            "практик",
            "сантехник",
            "инструктор",
            "хирург",
            "ветеринар",
            "фельдшер",
            "экзаменатор",
            "химик",
            "машинист",
            "оценщик",
            "диетолог",
            "архитектор",
            "парикмахер",
            "пекарь",
            "программист",
            "помощник юриста",
            "гигиенист",
            "ученый"
        ],
        "Female attributes": [
            "женский",
            "женщина",
            "девочка",
            "сестра",
            "она",
            "ее",
            "ее",
            "дочь"
        ],
        "Male attributes": [
            "мужской",
            "мужчина",
            "мальчик",
            "брат",
            "он",
            "его",
            "его",
            "сын"
        ],
        "W_key": "Карьеры",
        "attributes": "Женские атрибуты против Мужских атрибутов",
        "method": "wefat",
        "targets": "Карьеры"
    },
    "EuropeanAmerican_AfricanAmerican_Pleasant_Unpleasant": {
        "A_key": "Приятные",
        "African American names": [
            "алонзо",
            "джамел",
            "лерон",
            "перселл",
            "тео",
            "альфонс",
            "джером",
            "лерой",
            "расаан",
            "торранс",
            "дарнелл",
            "ламар",
            "лионель",
            "рашон",
            "тври",
            "деион",
            "ламонт",
            "малик",
            "терренс",
            "тайрон",
            "эверол",
            "лавон",
            "марцеллус",
            "террил",
            "уорделл",
            "айеша",
            "лашель",
            "нишель",
            "шерин",
            "темека",
            "эбони",
            "латиша",
            "шаникуа",
            "тамейша",
            "терета",
            "жасмин",
            "латонья",
            "шанис",
            "таниша",
            "тия",
            "лакиша",
            "латойя",
            "шариз",
            "ташика",
            "йоланда",
            "лашандра",
            "малика",
            "шавонн",
            "таванда",
            "иветт"
        ],
        "B_key": "Неприятные",
        "European American names": [
            "адам",
            "чип",
            "гарри",
            "джош",
            "роджер",
            "алан",
            "фрэнк",
            "йен",
            "джастин",
            "райан",
            "эндрю",
            "фред",
            "джек",
            "мэтью",
            "стивен",
            "брэд",
            "грег",
            "джед",
            "пол",
            "тодд",
            "брэндон",
            "хэнк",
            "джонатан",
            "питер",
            "вилбур",
            "аманда",
            "кортни",
            "хизер",
            "мелани",
            "сара",
            "эмбер",
            "кристал",
            "кэти",
            "мередит",
            "шаннон",
            "бетси",
            "донна",
            "кристин",
            "нэнси",
            "стефани",
            "бобби-сью",
            "эллен",
            "лаурен",
            "пегги",
            "сю-эллен",
            "колин",
            "эмма",
            "меган",
            "рейчел",
            "венди"
        ],
        "Pleasant": [
            "ласка",
            "свобода",
            "здоровье",
            "любовь",
            "мир",
            "радость",
            "друг",
            "небо",
            "верность",
            "удовольствие",
            "бриллиант",
            "нежный",
            "честный",
            "удачливый",
            "радуга",
            "диплом",
            "подарок",
            "честь",
            "чудо",
            "восход солнца",
            "семья",
            "счастливый",
            "смех",
            "рай",
            "отпуск"
        ],
        "Unpleasant": [
            "злоупотребление",
            "авария",
            "грязь",
            "убийство",
            "болезнь",
            "несчастный случай",
            "смерть",
            "горе",
            "яд",
            "вонь",
            "нападение",
            "катастрофа",
            "ненависть",
            "загрязнение",
            "трагедия",
            "бомба",
            "развод",
            "тюрьма",
            "нищета",
            "уродливый",
            "рак",
            "зло",
            "убить",
            "гнилой",
            "рвота"
        ],
        "X_key": "Европейскоамериканские имена",
        "Y_key": "Афроамериканские имена",
        "attributes": "Приятные против Неприятных",
        "method": "weat",
        "targets": "Европейскоамериканские имена против Афроамериканских имен"
    },
    "EuropeanAmerican_AfricanAmerican_Pleasant_Unpleasant_2": {
        "A_key": "Приятные",
        "African American names": [
            "дарнелл",
            "хаким",
            "джермейн",
            "карим",
            "джамал",
            "лерой",
            "рашид",
            "тремейн",
            "тайрон",
            "аиша",
            "эбони",
            "кейша",
            "кения",
            "латонья",
            "лакиша",
            "латойя",
            "тамика",
            "таниша"
        ],
        "B_key": "Неприятные",
        "European American names": [
            "брэд",
            "брендан",
            "джеффри",
            "грег",
            "бретт",
            "джей",
            "мэтью",
            "нил",
            "тодд",
            "эллисон",
            "энн",
            "кэрри",
            "эмма",
            "джилл",
            "лори",
            "кристен",
            "мередит",
            "сара"
        ],
        "Pleasant": [
            "ласка",
            "свобода",
            "здоровье",
            "любовь",
            "мир",
            "радость",
            "друг",
            "небо",
            "верность",
            "удовольствие",
            "бриллиант",
            "нежный",
            "честный",
            "удачливый",
            "радуга",
            "диплом",
            "подарок",
            "честь",
            "чудо",
            "восход солнца",
            "семья",
            "счастливый",
            "смех",
            "рай",
            "отпуск",
            "радость",
            "любовь",
            "мир",
            "прекрасный",
            "удовольствие",
            "друг",
            "смех",
            "счастливый"
        ],
        "Unpleasant": [
            "злоупотребление",
            "авария",
            "грязь",
            "убийство",
            "болезнь",
            "несчастный случай",
            "смерть",
            "горе",
            "яд",
            "вонь",
            "нападение",
            "катастрофа",
            "ненависть",
            "загрязнение",
            "трагедия",
            "бомба",
            "развод",
            "тюрьма",
            "нищета",
            "уродливый",
            "рак",
            "зло",
            "убить",
            "гнилой",
            "рвота",
            "агония",
            "ужасный",
            "ужасный",
            "противный",
            "зло",
            "война",
            "ужасный",
            "неудача"
        ],
        "X_key": "Европейскоамериканские имена",
        "Y_key": "Афроамериканские имена",
        "attributes": "Приятные против Неприятных",
        "method": "weat",
        "targets": "Европейскоамериканские имена против Афроамериканских имен"
    },
    "Flowers_Insects_Pleasant_Unpleasant": {
        "A_key": "Приятные",
        "B_key": "Неприятные",
        "Flowers": [
            "астра",
            "клевер",
            "гиацинт",
            "бархатцы",
            "мак",
            "азалия",
            "крокус",
            "ирис",
            "орхидея",
            "роза",
            "колокольчик",
            "нарцисс",
            "сирень",
            "анютины глазки",
            "тюльпан",
            "лютик",
            "маргаритка",
            "лилия",
            "пион",
            "фиалка",
            "гвоздика",
            "гладиолус",
            "магнолия",
            "петуния",
            "цинния"
        ],
        "Insects": [
            "муравей",
            "гусеница",
            "блоха",
            "саранча",
            "паук",
            "клоп",
            "сороконожка",
            "муха",
            "личинка",
            "тарантул",
            "пчела",
            "таракан",
            "мошка",
            "комар",
            "термит",
            "жук",
            "сверчок",
            "шершень",
            "мотылек",
            "оса",
            "муха цеце",
            "стрекоза",
            "овод",
            "таракан",
            "долгоносик"
        ],
        "Pleasant": [
            "ласка",
            "свобода",
            "здоровье",
            "любовь",
            "мир",
            "радость",
            "друг",
            "небо",
            "верность",
            "удовольствие",
            "бриллиант",
            "нежный",
            "честный",
            "удачливый",
            "радуга",
            "диплом",
            "подарок",
            "честь",
            "чудо",
            "восход солнца",
            "семья",
            "счастливый",
            "смех",
            "рай",
            "отпуск"
        ],
        "Unpleasant": [
            "злоупотребление",
            "авария",
            "грязь",
            "убийство",
            "болезнь",
            "несчастный случай",
            "смерть",
            "горе",
            "яд",
            "вонь",
            "нападение",
            "катастрофа",
            "ненависть",
            "загрязнение",
            "трагедия",
            "развод",
            "тюрьма",
            "нищета",
            "уродливый",
            "рак",
            "убить",
            "гнилой",
            "рвота",
            "агония",
            "тюрьма"
        ],
        "X_key": "Цветы",
        "Y_key": "Насекомые",
        "attributes": "Приятные против Неприятных",
        "method": "weat",
        "targets": "Цветы против Насекомых"
    },
    "Male_Female_Career_Family": {
        "A_key": "Слова о карьере",
        "B_key": "Слова о семье",
        "Career words": [
            "исполнительный",
            "управление",
            "профессионал",
            "корпорация",
            "зарплата",
            "офис",
            "бизнес",
            "карьера"
        ],
        "Family words": [
            "дом",
            "родители",
            "дети",
            "семья",
            "кузены",
            "брак",
            "свадьба",
            "родственники"
        ],
        "Female names": [
            "эми",
            "джоан",
            "лиза",
            "сара",
            "диана",
            "кейт",
            "энн",
            "донна"
        ],
        "Male names": [
            "джон",
            "пол",
            "майк",
            "кевин",
            "стив",
            "грег",
            "джефф",
            "билл"
        ],
        "X_key": "Мужские имена",
        "Y_key": "Женские имена",
        "attributes": "Слова о карьере против Слов о семье",
        "method": "weat",
        "targets": "Мужские имена против Женских имен"
    },
    "Math_Arts_Male_Female": {
        "A_key": "Мужские атрибуты",
        "Arts Words": [
            "поэзия",
            "искусство",
            "танец",
            "литература",
            "роман",
            "симфония",
            "драма",
            "скульптура"
        ],
        "B_key": "Женские атрибуты",
        "Female attributes": [
            "женский",
            "женщина",
            "девочка",
            "сестра",
            "она",
            "ее",
            "ее",
            "дочь"
        ],
        "Male attributes": [
            "мужской",
            "мужчина",
            "мальчик",
            "брат",
            "он",
            "его",
            "его",
            "сын"
        ],
        "Math words": [
            "математика",
            "алгебра",
            "геометрия",
            "исчисление",
            "уравнения",
            "вычисление",
            "числа",
            "сложение"
        ],
        "X_key": "Слова математики",
        "Y_key": "Слова искусства",
        "attributes": "Мужские атрибуты против Женских атрибутов",
        "method": "weat",
        "targets": "Слова математики против Слов искусства"
    },
    "MusicalInstruments_Weapons_Pleasant_Unpleasant": {
        "A_key": "Приятные",
        "B_key": "Неприятные",
        "Musical instruments": [
            "волынка",
            "виолончель",
            "гитара",
            "лютня",
            "тромбон",
            "банджо",
            "кларнет",
            "гармоника",
            "мандолина",
            "труба",
            "фагот",
            "барабан",
            "арфа",
            "гобой",
            "туба",
            "колокол",
            "скрипка",
            "клавесин",
            "пианино",
            "альт",
            "бонго",
            "флейта",
            "горн",
            "саксофон",
            "скрипка"
        ],
        "Pleasant": [
            "ласка",
            "свобода",
            "здоровье",
            "любовь",
            "мир",
            "радость",
            "друг",
            "небо",
            "верность",
            "удовольствие",
            "бриллиант",
            "нежный",
            "честный",
            "удачливый",
            "радуга",
            "диплом",
            "подарок",
            "честь",
            "чудо",
            "восход солнца",
            "семья",
            "счастливый",
            "смех",
            "рай",
            "отпуск"
        ],
        "Unpleasant": [
            "злоупотребление",
            "авария",
            "грязь",
            "убийство",
            "болезнь",
            "несчастный случай",
            "смерть",
            "горе",
            "яд",
            "вонь",
            "нападение",
            "катастрофа",
            "ненависть",
            "загрязнение",
            "трагедия",
            "развод",
            "тюрьма",
            "нищета",
            "уродливый",
            "рак",
            "убить",
            "гнилой",
            "рвота",
            "агония",
            "тюрьма"
        ],
        "Weapons": [
            "стрела",
            "дубинка",
            "пистолет",
            "ракета",
            "копье",
            "топор",
            "кинжал",
            "гарпун",
            "пистолет",
            "меч",
            "лезвие",
            "динамит",
            "топор",
            "винтовка",
            "танк",
            "бомба",
            "огнестрельное оружие",
            "нож",
            "дробовик",
            "слезоточивый газ",
            "пушка",
            "граната",
            "булава",
            "рогатка",
            "кнут"
        ],
        "X_key": "Музыкальные инструменты",
        "Y_key": "Оружие",
        "attributes": "Приятные против Неприятных",
        "method": "weat",
        "targets": "Музыкальные инструменты против Оружия"
    },
    "Names_Female_Male": {
        "A_key": "Женские атрибуты",
        "B_key": "Мужские атрибуты",
        "Female attributes": [
            "женский",
            "женщина",
            "девочка",
            "сестра",
            "она",
            "ее",
            "ее",
            "дочь"
        ],
        "Male attributes": [
            "мужской",
            "мужчина",
            "мальчик",
            "брат",
            "он",
            "его",
            "его",
            "сын"
        ],
        "Names": [
            "келли",
            "трейси",
            "джейми",
            "джеки",
            "джесси",
            "кортни",
            "линн",
            "тейлор",
            "лесли",
            "шеннон",
            "стейси",
            "джесси",
            "шон",
            "стейси",
            "кэйси",
            "бобби",
            "терри",
            "ли",
            "эшли",
            "эдди",
            "крис",
            "джоди",
            "пат",
            "кэри",
            "уилли",
            "морган",
            "робби",
            "джоан",
            "алексис",
            "крис",
            "фрэнки",
            "бобби",
            "дэйл",
            "робин",
            "билли",
            "адриан",
            "ким",
            "хайме",
            "джин",
            "фрэнсис",
            "мэрион",
            "дана",
            "рене",
            "джонни",
            "джордан",
            "кармен",
            "олли",
            "доминик",
            "джимми",
            "шелби"
        ],
        "W_key": "Имена",
        "attributes": "Женские атрибуты против Мужских атрибутов",
        "method": "wefat",
        "targets": "Имена"
    },
    "Science_Arts_Male_Female": {
        "A_key": "Мужские атрибуты",
        "Arts words": [
            "поэзия",
            "искусство",
            "шекспир",
            "танец",
            "литература",
            "роман",
            "симфония",
            "драма"
        ],
        "B_key": "Женские атрибуты",
        "Female attributes": [
            "сестра",
            "мать",
            "тетка",
            "бабушка",
            "дочь",
            "она",
            "ее",
            "ее"
        ],
        "Male attributes": [
            "брат",
            "отец",
            "дядя",
            "дедушка",
            "сын",
            "он",
            "его",
            "его"
        ],
        "Science words": [
            "наука",
            "технология",
            "физика",
            "химия",
            "эйнштейн",
            "наса",
            "эксперимент",
            "астрономия"
        ],
        "X_key": "Слова науки",
        "Y_key": "Слова искусства",
        "attributes": "Мужские атрибуты против Женских атрибутов",
        "method": "weat",
        "targets": "Слова науки против Слов искусства"
    }
}